MANIFEST.in
README.rst
egggitinfo.py
setup.py
egggitinfo.egg-info/PKG-INFO
egggitinfo.egg-info/SOURCES.txt
egggitinfo.egg-info/dependency_links.txt
egggitinfo.egg-info/entry_points.txt
egggitinfo.egg-info/git_info.txt
egggitinfo.egg-info/top_level.txt