Metadata-Version: 1.0
Name: egggitinfo
Version: 0.1
Summary: Plants some git-related data into the .egg-info directory of a python package.
Home-page: UNKNOWN
Author: UNKNOWN
Author-email: UNKNOWN
License: UNKNOWN
Platform: UNKNOWN
